pygame_retro_games-0.0.8.dist-info/licenses/LICENSE.txt
pygames/__init__.py
pygames/__main__.py
pygames/bounce/__init__.py
pygames/bounce/bloop.ogg
pygames/bounce/coin.ogg
pygames/bounce/main.py
pygames/bounce/munch.ogg
pygames/bounce/music.ogg
pygames/invaders/__init__.py
pygames/invaders/alien.ogg
pygames/invaders/gameover.ogg
pygames/invaders/invader-1.png
pygames/invaders/invader-2.png
pygames/invaders/invader-3.png
pygames/invaders/laser.ogg
pygames/invaders/main.py
pygames/invaders/tank-1.png
pygame_retro_games-0.0.8.dist-info/METADATA
pygame_retro_games-0.0.8.dist-info/WHEEL
pygame_retro_games-0.0.8.dist-info/entry_points.txt
pygame_retro_games-0.0.8.dist-info/top_level.txt
pygame_retro_games-0.0.8.dist-info/RECORD
