Metadata-Version: 2.4
Name: pygame-retro-games
Version: 0.0.8
Summary: PyGame Retro Games
Author-email: David <c0d3@gpobox.net>
Maintainer-email: David <c0d3@gpobox.net>
License-Expression: MIT
Project-URL: Homepage, https://github.com/bbc6502/pygames
Project-URL: Bug Tracker, https://github.com/bbc6502/pygames/issues
Keywords: games
Classifier: Programming Language :: Python :: 3
Classifier: Operating System :: OS Independent
Classifier: Development Status :: 3 - Alpha
Classifier: Natural Language :: English
Classifier: Operating System :: POSIX :: Linux
Classifier: Topic :: Games/Entertainment
Requires-Python: >=3.11
License-File: LICENSE.txt
Requires-Dist: pygame<3.0,>=2.6
Requires-Dist: numpy<3,>=2.2
Dynamic: license-file
